fh_utils/__init__.py
fh_utils/cli.py
fh_utils/constants.py
fh_utils/icons.py
fh_utils/ipython_ext.py
fh_utils/server.py
fh_utils/tailwind.py
fh_utils-0.5.0.dist-info/METADATA
fh_utils-0.5.0.dist-info/WHEEL
fh_utils-0.5.0.dist-info/entry_points.txt
fh_utils-0.5.0.dist-info/licenses/LICENSE
fh_utils-0.5.0.dist-info/RECORD
