Metadata-Version: 2.3
Name: fh_utils
Version: 0.5.0
Summary: A collection of utilities for FastHTML projects
Project-URL: Homepage, https://phihung.github.io/fh_utils/
Project-URL: Source, https://github.com/phihung/fh_utils
License-File: LICENSE
Requires-Python: >=3.10
Requires-Dist: diskcache>=5.6.3
Requires-Dist: python-fasthtml>=0.8.0
Requires-Dist: typer>=0.12.5
